mochart
tests
