Metadata-Version: 2.1
Name: mochart
Version: 0.1.1
Summary: Music online charts.
Home-page: https://github.com/hyunchel/mochart
Author: Hyunchel Kim
Author-email: hyunchel.inbox@gmail.com
License: MIT
Project-URL: Bug Tracker, https://github.com/hyunchel/mochart/issues
Project-URL: Documentation, https://github.com/hyunchel/mochart/README.md
Project-URL: Source Code, https://github.com/hyunchel/mochart
Keywords: music online chart ranking melon mnet naver gaon oricon
Platform: UNKNOWN
